[
  {
    "type": "promoter",
    "attributes": {
      "id": "346cfe43-7986-466b-86b0-b8a24ea78df0",
      "name": "n1",
      "organization": "o1",
      "email": "e@m.com"
    },
    "include": {
      "promoter": [

      ]
    }
  },
  {
    "type": "promoter",
    "attributes": {
      "id": "9891168a-5f55-4087-bbc9-e1b932a853c5",
      "name": "n1",
      "organization": "o2",
      "email": "2@m.com"
    },
    "include": {
      "promoter": [

      ]
    }
  },
  {
    "type": "promoter",
    "attributes": {
      "id": "b7dec1bf-44d3-411d-b15b-e089e035ec8b",
      "name": "n1",
      "organization": "o3",
      "email": "3@m.com"
    },
    "include": {
      "promoter": [

      ]
    }
  },
  {
    "type": "promoter",
    "attributes": {
      "id": "00a8b640-65ce-46e3-9ff0-5b72fee3dfb0",
      "name": "P1",
      "organization": "1",
      "email": "1@m.com"
    },
    "include": {
      "promoter": [
        {
          "type": "promotion",
          "attributes": {
            "id": 7,
            "title": "Lol",
            "description": "Dont @ me"
          },
          "include": {
            "promoter": "00a8b640-65ce-46e3-9ff0-5b72fee3dfb0",
            "tags": [

            ]
          }
        }
      ]
    }
  },
  {
    "type": "promoter",
    "attributes": {
      "id": "7f72c0b9-a089-4815-b5d2-70ade81b58b1",
      "name": "Synergized",
      "organization": "Ullrich, Treutel and Koss",
      "email": "juanita_jerde@mante.org"
    },
    "include": {
      "promoter": [

      ]
    }
  },
  {
    "type": "promoter",
    "attributes": {
      "id": "3fe40ac0-fd1c-4b46-9ada-0fcd7eb57b76",
      "name": "Ameliorated",
      "organization": "Runolfsdottir, Moore and Becker",
      "email": "viviana.beahan@halvorson.com"
    },
    "include": {
      "promoter": [

      ]
    }
  },
  {
    "type": "promoter",
    "attributes": {
      "id": "306f32af-7dbe-4af9-8741-57526e8ebe67",
      "name": "stable",
      "organization": "Jast-Yost",
      "email": "florene@nicolas.io"
    },
    "include": {
      "promoter": [

      ]
    }
  },
  {
    "type": "promoter",
    "attributes": {
      "id": "7bd8c10c-22da-4b55-beeb-829fe057bd44",
      "name": "Triple-buffered",
      "organization": "Toy, Conn and Osinski",
      "email": "shameka@schuster-franecki.name"
    },
    "include": {
      "promoter": [

      ]
    }
  },
  {
    "type": "promoter",
    "attributes": {
      "id": "1bac7a00-6594-4f8b-a4fa-38999df5dd04",
      "name": "Upgradable",
      "organization": "Kunze-Stamm",
      "email": "basil@parker.net"
    },
    "include": {
      "promoter": [

      ]
    }
  },
  {
    "type": "promoter",
    "attributes": {
      "id": "fee4dd61-f082-4905-a085-1bb8b48a7edc",
      "name": "function",
      "organization": "Farrell Inc",
      "email": "lorenzo.white@hudson.info"
    },
    "include": {
      "promoter": [

      ]
    }
  },
  {
    "type": "promoter",
    "attributes": {
      "id": "0e6aad82-55ee-4697-bb08-06b93b3f933e",
      "name": "Re-contextualized",
      "organization": "Lakin, Cremin and Kreiger",
      "email": "jerold_bednar@reichel.com"
    },
    "include": {
      "promoter": [

      ]
    }
  },
  {
    "type": "promoter",
    "attributes": {
      "id": "2a84e0bc-8b63-4fa1-aca4-f31ffcfc8253",
      "name": "Secured",
      "organization": "Schaden Inc",
      "email": "michael@rutherford.org"
    },
    "include": {
      "promoter": [

      ]
    }
  },
  {
    "type": "promoter",
    "attributes": {
      "id": "153737ee-c106-4bec-b217-8688d6a5342f",
      "name": "Switchable",
      "organization": "Brown-Ankunding",
      "email": "rolf.robel@turner.co"
    },
    "include": {
      "promoter": [

      ]
    }
  },
  {
    "type": "promoter",
    "attributes": {
      "id": "4e05e3e0-07ee-4cfd-b030-838d2c1fb93c",
      "name": "customer loyalty",
      "organization": "Towne Inc",
      "email": "franklin@huels-swaniawski.biz"
    },
    "include": {
      "promoter": [

      ]
    }
  },
  {
    "type": "promoter",
    "attributes": {
      "id": "872e0bdf-623c-4785-b535-ed6d7fd633c9",
      "name": "conglomeration",
      "organization": "Blick, Schaefer and Larkin",
      "email": "roland_fay@ohara.info"
    },
    "include": {
      "promoter": [

      ]
    }
  },
  {
    "type": "promoter",
    "attributes": {
      "id": "4f251f16-d6fd-48a5-ac0e-5fcc4195a43a",
      "name": "hardware",
      "organization": "Wilderman Group",
      "email": "kimber@berge.name"
    },
    "include": {
      "promoter": [

      ]
    }
  },
  {
    "type": "promoter",
    "attributes": {
      "id": "39e3e505-af0c-4021-8a0c-0d288ea900dc",
      "name": "reciprocal",
      "organization": "Russel-Casper",
      "email": "branden@franecki-schinner.biz"
    },
    "include": {
      "promoter": [

      ]
    }
  },
  {
    "type": "promoter",
    "attributes": {
      "id": "8e4bea7b-382a-4b60-a423-371e7ffffa1f",
      "name": "leverage",
      "organization": "Connelly-Paucek",
      "email": "kimbery@miller-ratke.io"
    },
    "include": {
      "promoter": [

      ]
    }
  },
  {
    "type": "promoter",
    "attributes": {
      "id": "db3c82cb-8e57-41ad-8cf1-582f4bfae6c6",
      "name": "methodical",
      "organization": "Doyle, Waelchi and Wuckert",
      "email": "charley@batz-feil.io"
    },
    "include": {
      "promoter": [

      ]
    }
  },
  {
    "type": "promoter",
    "attributes": {
      "id": "efda0a8c-fb86-45dd-9a59-76e2bf2649f1",
      "name": "Organic",
      "organization": "Jast-Kirlin",
      "email": "alonzo_wisoky@price.io"
    },
    "include": {
      "promoter": [

      ]
    }
  },
  {
    "type": "promoter",
    "attributes": {
      "id": "d3381b93-d3bc-4979-bb4b-418916d25e83",
      "name": "database",
      "organization": "Kuhic-Robel",
      "email": "maybell@dickens.net"
    },
    "include": {
      "promoter": [

      ]
    }
  },
  {
    "type": "promoter",
    "attributes": {
      "id": "208ab646-7ed3-4954-856e-485346fa5e96",
      "name": "User-friendly",
      "organization": "Kiehn-Lynch",
      "email": "mercedez.barrows@lindgren-auer.info"
    },
    "include": {
      "promoter": [

      ]
    }
  },
  {
    "type": "promoter",
    "attributes": {
      "id": "a0bd9ec4-7fd1-4690-b185-c7a92a88331c",
      "name": "Organized",
      "organization": "Waelchi-Schuppe",
      "email": "kirby@shields-gerlach.biz"
    },
    "include": {
      "promoter": [

      ]
    }
  },
  {
    "type": "promoter",
    "attributes": {
      "id": "e5cfc13e-fb60-403e-a706-0a8305c7337b",
      "name": "6th generation",
      "organization": "Von and Sons",
      "email": "mason@bauch.info"
    },
    "include": {
      "promoter": [

      ]
    }
  },
  {
    "type": "promoter",
    "attributes": {
      "id": "5fc5c95e-c2c8-4182-92a9-6d92155ed649",
      "name": "success",
      "organization": "Gorczany, Okuneva and Bergstrom",
      "email": "janetta@lakin.name"
    },
    "include": {
      "promoter": [

      ]
    }
  },
  {
    "type": "promoter",
    "attributes": {
      "id": "d7285465-2ab4-418b-9004-cfa75dc72992",
      "name": "zero tolerance",
      "organization": "Reynolds Inc",
      "email": "derek@beatty.org"
    },
    "include": {
      "promoter": [

      ]
    }
  },
  {
    "type": "promoter",
    "attributes": {
      "id": "9be5be27-254a-4fce-9fb5-d1e8b8da8229",
      "name": "mobile",
      "organization": "Daniel, Mitchell and Keebler",
      "email": "tod.rodriguez@weimann-koepp.info"
    },
    "include": {
      "promoter": [

      ]
    }
  },
  {
    "type": "promoter",
    "attributes": {
      "id": "faab9d3a-a189-4a66-8f2b-797ac35ae41c",
      "name": "homogeneous",
      "organization": "Murazik-Botsford",
      "email": "maurice.klocko@christiansen-hermiston.info"
    },
    "include": {
      "promoter": [

      ]
    }
  },
  {
    "type": "promoter",
    "attributes": {
      "id": "1334cd04-16bc-43f2-9a54-45c489524af4",
      "name": "Total",
      "organization": "Smith-Miller",
      "email": "elaine_hayes@legros.org"
    },
    "include": {
      "promoter": [

      ]
    }
  },
  {
    "type": "promoter",
    "attributes": {
      "id": "bac08ba9-d8eb-4a35-88ef-63f8acae4949",
      "name": "client-driven",
      "organization": "Hilpert-Murazik",
      "email": "carlos_gutmann@gottlieb.biz"
    },
    "include": {
      "promoter": [

      ]
    }
  },
  {
    "type": "promoter",
    "attributes": {
      "id": "7f4826da-f242-49aa-9201-314e071fcdd5",
      "name": "Up-sized",
      "organization": "Yundt-Ruecker",
      "email": "alvin@nienow-rice.name"
    },
    "include": {
      "promoter": [

      ]
    }
  },
  {
    "type": "promoter",
    "attributes": {
      "id": "0f07e93d-8451-4e76-a503-0a26478f156b",
      "name": "time-frame",
      "organization": "Koelpin-Hodkiewicz",
      "email": "vi.wisoky@heidenreich-lakin.biz"
    },
    "include": {
      "promoter": [

      ]
    }
  },
  {
    "type": "promoter",
    "attributes": {
      "id": "c045ff07-6f1d-4d71-a9f7-92a85d9d5ef6",
      "name": "methodical",
      "organization": "Schulist and Sons",
      "email": "jeffery.ruecker@beier.info"
    },
    "include": {
      "promoter": [

      ]
    }
  },
  {
    "type": "promoter",
    "attributes": {
      "id": "1e4af3ac-22ae-401e-bb98-e76127878551",
      "name": "Managed",
      "organization": "Spinka Group",
      "email": "wai_dickinson@bernhard.biz"
    },
    "include": {
      "promoter": [

      ]
    }
  }
]